odbc2orm/__init__.py
odbc2orm/__main__.py
odbc2orm/config.py
odbc2orm/convert.py
odbc2orm/database.py
odbc2orm/template.py
odbc2orm/version.py
odbc2orm-1.0.7.dist-info/METADATA
odbc2orm-1.0.7.dist-info/WHEEL
odbc2orm-1.0.7.dist-info/entry_points.txt
odbc2orm-1.0.7.dist-info/top_level.txt
odbc2orm-1.0.7.dist-info/RECORD
