Metadata-Version: 2.1
Name: odbc2orm
Version: 1.0.7
Summary: Convert ODBC schema to ORM
Home-page: https://github.com/pe2mbs/odbc2orm
Author: Marc Bertens-Nguyen
Author-email: m.bertens@pe2mbs.nl
Project-URL: Source Public, https://github.com/pe2mbs/odbc2orm/
Project-URL: Bug Reports, https://github.com/pe2mbs/odbc2orm/issues
Project-URL: Say Thanks!, https://github.com/pe2mbs/odbc2orm/saythanks
Keywords: odbc sqlalchemu orm
Classifier: Environment :: Console
Classifier: Operating System :: Microsoft :: Windows
Classifier: Intended Audience :: Developers
Classifier: License :: OSI Approved :: GNU General Public License (GPL)
Classifier: Programming Language :: Python :: 3
Requires-Python: >=3.6
Requires-Dist: PyYAML
Requires-Dist: pyodbc
Requires-Dist: Mako
